rsb_git/__init__.py
rsb_git/_git.py
rsb_git/_version.py
rspython-0.1.0.dist-info/LICENSE
rspython-0.1.0.dist-info/METADATA
rspython-0.1.0.dist-info/WHEEL
rspython-0.1.0.dist-info/top_level.txt
rspython-0.1.0.dist-info/RECORD
